pycaching/__init__.py
pycaching/caching.py
pycaching_elunico-1.3.2.dist-info/LICENSE
pycaching_elunico-1.3.2.dist-info/METADATA
pycaching_elunico-1.3.2.dist-info/WHEEL
pycaching_elunico-1.3.2.dist-info/top_level.txt
pycaching_elunico-1.3.2.dist-info/RECORD
